files/restoring_div.v
// ============================================================
// Unitate de Impartire - Restoring Division (FIXED)
// Dividend: 8-bit unsigned, Divisor: 8-bit unsigned
// ============================================================
module restoring_div(
    input        clk,
    input        reset,
    input        start,
    input  [7:0] dividend,
    input  [7:0] divisor,
    output reg [7:0] quotient,
    output reg [7:0] remainder,
    output reg       done,
    output           div_by_zero
);
    reg [7:0]  A;       // Remainder partial (acumulator)
    reg [7:0]  Q;       // Quotient (initial = dividend)
    reg [7:0]  M;       // Divisor
    reg [3:0]  count;
    reg        running;

    assign div_by_zero = (divisor == 8'b0);

    always @(posedge clk) begin
        if (reset) begin
            A         <= 8'b0;
            Q         <= 8'b0;
            M         <= 8'b0;
            count     <= 4'd0;
            running   <= 1'b0;
            done      <= 1'b0;
            quotient  <= 8'b0;
            remainder <= 8'b0;
        end
        else if (start && !running && !div_by_zero) begin
            A         <= 8'b0;
            Q         <= dividend;
            M         <= divisor;
            count     <= 4'd0;
            running   <= 1'b1;
            done      <= 1'b0;
        end
        else if (running) begin
            // --- Pas Restoring Division ---
            // 1. Shift stanga A:Q cu 1 bit
            // 2. A = A - M
            // 3. Daca A[7]=1 (negativ): restore A (A = A + M), Q[0] = 0
            //    Daca A[7]=0 (pozitiv): Q[0] = 1
            begin : div_step
                reg [7:0] A_shift;
                reg [7:0] A_sub;
                reg [7:0] A_next;
                reg       q_bit;

                // Shift stanga A:Q
                A_shift = {A[6:0], Q[7]};
                Q       <= {Q[6:0], 1'b0};

                // Scadere
                A_sub = A_shift - M;

                if (A_sub[7] == 1'b1) begin
                    // Negativ => restore
                    A_next = A_shift;  // restore
                    q_bit  = 1'b0;
                end else begin
                    A_next = A_sub;
                    q_bit  = 1'b1;
                end

                A    <= A_next;
                Q[0] <= q_bit;
            end

            count <= count + 4'd1;

            if (count == 4'd7) begin
                running <= 1'b0;
                done    <= 1'b1;
            end
        end
        else if (done) begin
            quotient  <= Q;
            remainder <= A;
            done      <= 1'b0;
        end
    end

endmodule

files/booth_mult.v
// ============================================================
// Unitate de Inmultire - Booth Radix-2 (FIXED)
// Un singur always block pentru a evita conflicte
// ============================================================
module booth_mult(
    input        clk,
    input        reset,
    input        start,
    input  [7:0] multiplicand,
    input  [7:0] multiplier,
    output reg [15:0] product,
    output reg        done
);
    reg [8:0] A;      // 9 biti (bit extra pentru semn la add/sub)
    reg [7:0] Q;
    reg       Q1;
    reg [7:0] M;
    reg [3:0] count;
    reg       running;

    wire [8:0] M_ext  = {{1{multiplicand[7]}}, multiplicand}; // sign extend M la 9 biti

    always @(posedge clk) begin
        if (reset) begin
            A       <= 9'b0;
            Q       <= 8'b0;
            M       <= 8'b0;
            Q1      <= 1'b0;
            count   <= 4'd0;
            running <= 1'b0;
            done    <= 1'b0;
            product <= 16'b0;
        end
        else if (start && !running) begin
            A       <= 9'b0;
            Q       <= multiplier;
            M       <= multiplicand;
            Q1      <= 1'b0;
            count   <= 4'd0;
            running <= 1'b1;
            done    <= 1'b0;
            product <= 16'b0;
        end
        else if (running) begin
            // --- Pasul 1: Operatie Booth pe A ---
            case ({Q[0], Q1})
                2'b01: begin  // +M
                    // Shift aritmetic dupa adunare
                    begin : add_shift
                        reg [8:0] A_new;
                        A_new = A + {{1{M[7]}}, M};
                        Q1 <= Q[0];
                        Q  <= {A_new[0], Q[7:1]};
                        A  <= {A_new[8], A_new[8:1]};
                    end
                end
                2'b10: begin  // -M
                    begin : sub_shift
                        reg [8:0] A_new;
                        A_new = A - {{1{M[7]}}, M};
                        Q1 <= Q[0];
                        Q  <= {A_new[0], Q[7:1]};
                        A  <= {A_new[8], A_new[8:1]};
                    end
                end
                default: begin  // 00 sau 11 - doar shift
                    Q1 <= Q[0];
                    Q  <= {A[0], Q[7:1]};
                    A  <= {A[8], A[8:1]};
                end
            endcase

            count <= count + 4'd1;

            if (count == 4'd7) begin
                running <= 1'b0;
                done    <= 1'b1;
            end
        end
        else if (done) begin
            product <= {A[7:0], Q};
            done    <= 1'b0;
        end
    end

endmodule

files/full_adder.v
// ============================================================
// Full Adder - 1 bit
// ============================================================
module full_adder(
    input  a,
    input  b,
    input  cin,
    output sum,
    output cout
);
    wire w1, w2, w3;

    xor U1(w1, a, b);
    xor U2(sum, w1, cin);
    and U3(w2, a, b);
    and U4(w3, w1, cin);
    or  U5(cout, w2, w3);

endmodule

files/adder_subtractor_8b.v
// ============================================================
// 8-bit Adder/Subtractor
// sub=0 => A+B, sub=1 => A-B (prin complementul fata de 2)
// ============================================================
module adder_subtractor_8b(
    input  [7:0] A,
    input  [7:0] B,
    input        sub,       // 0=adunare, 1=scadere
    output [7:0] result,
    output       cout,
    output       overflow
);
    wire [7:0] B_xor;
    wire [7:0] carry;
    wire       c_in;

    // Daca sub=1, inversam B (XOR cu 1) si cin=1 => complement fata de 2
    assign c_in = sub;

    xor XB0(B_xor[0], B[0], sub);
    xor XB1(B_xor[1], B[1], sub);
    xor XB2(B_xor[2], B[2], sub);
    xor XB3(B_xor[3], B[3], sub);
    xor XB4(B_xor[4], B[4], sub);
    xor XB5(B_xor[5], B[5], sub);
    xor XB6(B_xor[6], B[6], sub);
    xor XB7(B_xor[7], B[7], sub);

    full_adder FA0(A[0], B_xor[0], c_in,     result[0], carry[0]);
    full_adder FA1(A[1], B_xor[1], carry[0], result[1], carry[1]);
    full_adder FA2(A[2], B_xor[2], carry[1], result[2], carry[2]);
    full_adder FA3(A[3], B_xor[3], carry[2], result[3], carry[3]);
    full_adder FA4(A[4], B_xor[4], carry[3], result[4], carry[4]);
    full_adder FA5(A[5], B_xor[5], carry[4], result[5], carry[5]);
    full_adder FA6(A[6], B_xor[6], carry[5], result[6], carry[6]);
    full_adder FA7(A[7], B_xor[7], carry[6], result[7], cout);

    // Overflow: carry in != carry out la bitul de semn
    xor OVF(overflow, carry[6], cout);

endmodule

files/control_unit.v
// ============================================================
// Control Unit - FSM
// OpCode: 00=ADD, 01=SUB, 10=MUL (Booth), 11=DIV (Restoring)
// ============================================================
module control_unit(
    input      clk,
    input      reset,
    input      start,
    input [1:0] opcode,
    input      mul_done,
    input      div_done,

    output reg load_A,
    output reg load_B,
    output reg load_M,
    output reg load_Q,
    output reg shift_en,
    output reg mux_sel,
    output reg counter_en,
    output reg [1:0] alu_op,   // 00=add, 01=sub, 10=mul, 11=div
    output reg result_ready
);
    // State encoding
    parameter IDLE    = 3'd0;
    parameter LOAD    = 3'd1;
    parameter EXEC_AS = 3'd2;  // Add/Sub (1 ciclu)
    parameter EXEC_MU = 3'd3;  // Multiply (iterativ)
    parameter EXEC_DV = 3'd4;  // Divide (iterativ)
    parameter DONE    = 3'd5;

    reg [2:0] state, next_state;

    // State register
    always @(posedge clk) begin
        if (reset)
            state <= IDLE;
        else
            state <= next_state;
    end

    // Next state logic
    always @(*) begin
        next_state = state;
        case (state)
            IDLE:    if (start)           next_state = LOAD;
            LOAD:                         next_state = (opcode == 2'b00 || opcode == 2'b01) ?
                                                        EXEC_AS :
                                                       (opcode == 2'b10) ? EXEC_MU : EXEC_DV;
            EXEC_AS:                      next_state = DONE;
            EXEC_MU: if (mul_done)        next_state = DONE;
            EXEC_DV: if (div_done)        next_state = DONE;
            DONE:                         next_state = IDLE;
            default:                      next_state = IDLE;
        endcase
    end

    // Output logic
    always @(*) begin
        // Valori default
        load_A      = 1'b0;
        load_B      = 1'b0;
        load_M      = 1'b0;
        load_Q      = 1'b0;
        shift_en    = 1'b0;
        mux_sel     = 1'b0;
        counter_en  = 1'b0;
        alu_op      = opcode;
        result_ready = 1'b0;

        case (state)
            LOAD: begin
                load_A = 1'b1;
                load_B = 1'b1;
                load_M = (opcode == 2'b10 || opcode == 2'b11) ? 1'b1 : 1'b0;
                load_Q = (opcode == 2'b10 || opcode == 2'b11) ? 1'b1 : 1'b0;
            end
            EXEC_AS: begin
                mux_sel = (opcode == 2'b01) ? 1'b1 : 1'b0; // 1=sub
            end
            EXEC_MU: begin
                shift_en   = 1'b1;
                counter_en = 1'b1;
            end
            EXEC_DV: begin
                shift_en   = 1'b1;
                counter_en = 1'b1;
            end
            DONE: begin
                result_ready = 1'b1;
            end
        endcase
    end

endmodule

files/alu_8bit.v
// ============================================================
// ALU 8-BIT - Modul Top-Level (FIXED)
// OpCode: 00=ADD, 01=SUB, 10=MUL (Booth R2), 11=DIV (Restoring)
// ============================================================
module alu_8bit(
    input        clk,
    input        reset,
    input        start,
    input  [1:0] opcode,
    input  [7:0] input_A,
    input  [7:0] input_B,

    output [15:0] result,
    output [7:0]  quotient,
    output [7:0]  remainder,
    output        result_ready,
    output        div_by_zero,

    output        flag_N,
    output        flag_Z,
    output        flag_C,
    output        flag_V
);
    // ---- Semnale interne ----
    wire       load_A, load_B, load_M, load_Q;
    wire       shift_en, mux_sel, counter_en;
    wire [1:0] alu_op;
    wire       mul_done, div_done;

    wire [7:0] addsub_result;
    wire       addsub_cout, addsub_ovf;
    wire [15:0] mul_product;
    wire [7:0]  div_quotient, div_remainder;

    // ---- Control Unit ----
    control_unit CU(
        .clk(clk), .reset(reset), .start(start), .opcode(opcode),
        .mul_done(mul_done), .div_done(div_done),
        .load_A(load_A), .load_B(load_B),
        .load_M(load_M), .load_Q(load_Q),
        .shift_en(shift_en), .mux_sel(mux_sel),
        .counter_en(counter_en), .alu_op(alu_op),
        .result_ready(result_ready)
    );

    // ---- Adder/Subtractor 8b (combinational, foloseste input direct) ----
    adder_subtractor_8b ASU(
        .A(input_A),
        .B(input_B),
        .sub(opcode[0]),   // opcode=01 => sub=1
        .result(addsub_result),
        .cout(addsub_cout),
        .overflow(addsub_ovf)
    );

    // ---- Inmultire Booth Radix-2 ----
    booth_mult MULT(
        .clk(clk), .reset(reset),
        .start(start && (opcode == 2'b10)),
        .multiplicand(input_A),
        .multiplier(input_B),
        .product(mul_product),
        .done(mul_done)
    );

    // ---- Impartire Restoring ----
    restoring_div DIV(
        .clk(clk), .reset(reset),
        .start(start && (opcode == 2'b11)),
        .dividend(input_A),
        .divisor(input_B),
        .quotient(div_quotient),
        .remainder(div_remainder),
        .done(div_done),
        .div_by_zero(div_by_zero)
    );

    // ---- Result Bus ----
    assign result = (opcode == 2'b10) ? mul_product :
                    (opcode == 2'b11) ? {8'b0, div_quotient} :
                                        {8'b0, addsub_result};

    assign quotient  = div_quotient;
    assign remainder = div_remainder;

    // ---- Status Flags ----
    assign flag_N = addsub_result[7];
    assign flag_Z = (addsub_result == 8'b0);
    assign flag_C = addsub_cout;
    assign flag_V = addsub_ovf;

endmodule

files/tb_alu_8bit.v
// ============================================================
// Testbench - ALU 8-BIT (FIXED)
// ============================================================
`timescale 1ns/1ps

module tb_alu_8bit;

    reg        clk, reset, start;
    reg  [1:0] opcode;
    reg  [7:0] input_A, input_B;

    wire [15:0] result;
    wire [7:0]  quotient, remainder;
    wire        result_ready, div_by_zero;
    wire        flag_N, flag_Z, flag_C, flag_V;

    alu_8bit DUT(
        .clk(clk), .reset(reset), .start(start),
        .opcode(opcode), .input_A(input_A), .input_B(input_B),
        .result(result), .quotient(quotient), .remainder(remainder),
        .result_ready(result_ready), .div_by_zero(div_by_zero),
        .flag_N(flag_N), .flag_Z(flag_Z),
        .flag_C(flag_C), .flag_V(flag_V)
    );

    initial clk = 0;
    always #5 clk = ~clk;

    // Asteapta N cicluri de clock
    task wait_cycles;
        input integer n;
        integer i;
        begin
            for (i = 0; i < n; i = i + 1)
                @(posedge clk);
            #1;
        end
    endtask

    // Pulse start pentru 1 ciclu
    task do_start;
        begin
            @(posedge clk); #1;
            start = 1;
            @(posedge clk); #1;
            start = 0;
        end
    endtask

    integer pass_count;
    integer fail_count;

    initial begin
        $dumpfile("tb_alu_8bit.vcd");
        $dumpvars(0, tb_alu_8bit);

        pass_count = 0;
        fail_count = 0;

        // Reset
        reset = 1; start = 0;
        opcode = 2'b00; input_A = 0; input_B = 0;
        wait_cycles(3);
        reset = 0;
        wait_cycles(2);

        // ==========================================
        // ADUNARE
        // ==========================================
        $display("\n========== ADUNARE (ADD) ==========");

        // Test ADD 1: 15 + 27 = 42
        input_A = 8'd15; input_B = 8'd27; opcode = 2'b00;
        do_start; wait_cycles(3);
        if (result[7:0] == 8'd42) begin
            $display("[PASS] ADD  15 + 27 = %0d", result[7:0]);
            pass_count = pass_count + 1;
        end else begin
            $display("[FAIL] ADD  15 + 27 = %0d (asteptat 42)", result[7:0]);
            fail_count = fail_count + 1;
        end

        // Test ADD 2: 0 + 0 = 0 (flag Z)
        input_A = 8'd0; input_B = 8'd0; opcode = 2'b00;
        do_start; wait_cycles(3);
        if (result[7:0] == 8'd0 && flag_Z == 1) begin
            $display("[PASS] ADD   0 +  0 = %0d, Z=%b", result[7:0], flag_Z);
            pass_count = pass_count + 1;
        end else begin
            $display("[FAIL] ADD   0 +  0 = %0d, Z=%b", result[7:0], flag_Z);
            fail_count = fail_count + 1;
        end

        // Test ADD 3: 200 + 100 = 300 => carry out
        input_A = 8'd200; input_B = 8'd100; opcode = 2'b00;
        do_start; wait_cycles(3);
        if (flag_C == 1) begin
            $display("[PASS] ADD 200+100 carry C=%b, result=%0d", flag_C, result[7:0]);
            pass_count = pass_count + 1;
        end else begin
            $display("[FAIL] ADD 200+100 carry C=%b (asteptat 1)", flag_C);
            fail_count = fail_count + 1;
        end

        // ==========================================
        // SCADERE
        // ==========================================
        $display("\n========== SCADERE (SUB) ==========");

        // Test SUB 1: 50 - 20 = 30
        input_A = 8'd50; input_B = 8'd20; opcode = 2'b01;
        do_start; wait_cycles(3);
        if (result[7:0] == 8'd30) begin
            $display("[PASS] SUB  50 - 20 = %0d", result[7:0]);
            pass_count = pass_count + 1;
        end else begin
            $display("[FAIL] SUB  50 - 20 = %0d (asteptat 30)", result[7:0]);
            fail_count = fail_count + 1;
        end

        // Test SUB 2: 10 - 10 = 0 (flag Z)
        input_A = 8'd10; input_B = 8'd10; opcode = 2'b01;
        do_start; wait_cycles(3);
        if (result[7:0] == 8'd0 && flag_Z == 1) begin
            $display("[PASS] SUB  10 - 10 = %0d, Z=%b", result[7:0], flag_Z);
            pass_count = pass_count + 1;
        end else begin
            $display("[FAIL] SUB  10 - 10 = %0d, Z=%b", result[7:0], flag_Z);
            fail_count = fail_count + 1;
        end

        // Test SUB 3: 10 - 30 = -20 (flag N)
        input_A = 8'd10; input_B = 8'd30; opcode = 2'b01;
        do_start; wait_cycles(3);
        if (flag_N == 1) begin
            $display("[PASS] SUB  10 - 30 = %0d (negativ, N=%b)", $signed(result[7:0]), flag_N);
            pass_count = pass_count + 1;
        end else begin
            $display("[FAIL] SUB  10 - 30 = %0d (N=%b, asteptat N=1)", $signed(result[7:0]), flag_N);
            fail_count = fail_count + 1;
        end

        // ==========================================
        // INMULTIRE - Booth Radix-2
        // ==========================================
        $display("\n========== INMULTIRE - Booth Radix-2 ==========");

        // Test MUL 1: 6 x 7 = 42
        input_A = 8'd6; input_B = 8'd7; opcode = 2'b10;
        do_start; wait_cycles(20);
        if (result == 16'd42) begin
            $display("[PASS] MUL   6 x  7 = %0d", result);
            pass_count = pass_count + 1;
        end else begin
            $display("[FAIL] MUL   6 x  7 = %0d (asteptat 42)", result);
            fail_count = fail_count + 1;
        end

        // Test MUL 2: 0 x 255 = 0
        input_A = 8'd0; input_B = 8'd255; opcode = 2'b10;
        do_start; wait_cycles(20);
        if (result == 16'd0) begin
            $display("[PASS] MUL   0 x255 = %0d", result);
            pass_count = pass_count + 1;
        end else begin
            $display("[FAIL] MUL   0 x255 = %0d (asteptat 0)", result);
            fail_count = fail_count + 1;
        end

        // Test MUL 3: (-4) x 3 = -12
        input_A = 8'hFC; input_B = 8'd3; opcode = 2'b10;  // 0xFC = -4
        do_start; wait_cycles(20);
        if ($signed(result) == -16'd12) begin
            $display("[PASS] MUL  -4 x  3 = %0d", $signed(result));
            pass_count = pass_count + 1;
        end else begin
            $display("[FAIL] MUL  -4 x  3 = %0d (asteptat -12)", $signed(result));
            fail_count = fail_count + 1;
        end

        // Test MUL 4: 15 x 15 = 225
        input_A = 8'd15; input_B = 8'd15; opcode = 2'b10;
        do_start; wait_cycles(20);
        if (result == 16'd225) begin
            $display("[PASS] MUL  15 x 15 = %0d", result);
            pass_count = pass_count + 1;
        end else begin
            $display("[FAIL] MUL  15 x 15 = %0d (asteptat 225)", result);
            fail_count = fail_count + 1;
        end

        // ==========================================
        // IMPARTIRE - Restoring Division
        // ==========================================
        $display("\n========== IMPARTIRE - Restoring Division ==========");

        // Test DIV 1: 42 / 6 = 7 rest 0
        input_A = 8'd42; input_B = 8'd6; opcode = 2'b11;
        do_start; wait_cycles(20);
        if (quotient == 8'd7 && remainder == 8'd0) begin
            $display("[PASS] DIV  42 /  6 = %0d rest %0d", quotient, remainder);
            pass_count = pass_count + 1;
        end else begin
            $display("[FAIL] DIV  42 /  6 = %0d rest %0d (asteptat 7 rest 0)", quotient, remainder);
            fail_count = fail_count + 1;
        end

        // Test DIV 2: 17 / 5 = 3 rest 2
        input_A = 8'd17; input_B = 8'd5; opcode = 2'b11;
        do_start; wait_cycles(20);
        if (quotient == 8'd3 && remainder == 8'd2) begin
            $display("[PASS] DIV  17 /  5 = %0d rest %0d", quotient, remainder);
            pass_count = pass_count + 1;
        end else begin
            $display("[FAIL] DIV  17 /  5 = %0d rest %0d (asteptat 3 rest 2)", quotient, remainder);
            fail_count = fail_count + 1;
        end

        // Test DIV 3: 100 / 10 = 10 rest 0
        input_A = 8'd100; input_B = 8'd10; opcode = 2'b11;
        do_start; wait_cycles(20);
        if (quotient == 8'd10 && remainder == 8'd0) begin
            $display("[PASS] DIV 100 / 10 = %0d rest %0d", quotient, remainder);
            pass_count = pass_count + 1;
        end else begin
            $display("[FAIL] DIV 100 / 10 = %0d rest %0d (asteptat 10 rest 0)", quotient, remainder);
            fail_count = fail_count + 1;
        end

        // Test DIV 4: divide by zero
        input_A = 8'd10; input_B = 8'd0; opcode = 2'b11;
        do_start; wait_cycles(5);
        if (div_by_zero == 1) begin
            $display("[PASS] DIV  10 /  0 => div_by_zero=%b", div_by_zero);
            pass_count = pass_count + 1;
        end else begin
            $display("[FAIL] DIV  10 /  0 => div_by_zero=%b (asteptat 1)", div_by_zero);
            fail_count = fail_count + 1;
        end

        // ==========================================
        // SUMAR
        // ==========================================
        $display("\n==========================================");
        $display("REZULTATE: %0d PASS / %0d FAIL", pass_count, fail_count);
        $display("==========================================\n");

        $finish;
    end

endmodule

files/tb_alu_8bit.vcd
$date
	Sat Apr 18 18:34:49 2026
$end
$version
	Icarus Verilog
$end
$timescale
	1ps
$end
$scope module tb_alu_8bit $end
$var wire 1 ! result_ready $end
$var wire 16 " result [15:0] $end
$var wire 8 # remainder [7:0] $end
$var wire 8 $ quotient [7:0] $end
$var wire 1 % flag_Z $end
$var wire 1 & flag_V $end
$var wire 1 ' flag_N $end
$var wire 1 ( flag_C $end
$var wire 1 ) div_by_zero $end
$var reg 1 * clk $end
$var reg 8 + input_A [7:0] $end
$var reg 8 , input_B [7:0] $end
$var reg 2 - opcode [1:0] $end
$var reg 1 . reset $end
$var reg 1 / start $end
$var integer 32 0 fail_count [31:0] $end
$var integer 32 1 pass_count [31:0] $end
$scope module DUT $end
$var wire 1 * clk $end
$var wire 1 ( flag_C $end
$var wire 1 & flag_V $end
$var wire 8 2 input_A [7:0] $end
$var wire 8 3 input_B [7:0] $end
$var wire 2 4 opcode [1:0] $end
$var wire 8 5 quotient [7:0] $end
$var wire 8 6 remainder [7:0] $end
$var wire 1 . reset $end
$var wire 1 / start $end
$var wire 1 7 shift_en $end
$var wire 1 ! result_ready $end
$var wire 16 8 result [15:0] $end
$var wire 1 9 mux_sel $end
$var wire 16 : mul_product [15:0] $end
$var wire 1 ; mul_done $end
$var wire 1 < load_Q $end
$var wire 1 = load_M $end
$var wire 1 > load_B $end
$var wire 1 ? load_A $end
$var wire 1 % flag_Z $end
$var wire 1 ' flag_N $end
$var wire 8 @ div_remainder [7:0] $end
$var wire 8 A div_quotient [7:0] $end
$var wire 1 B div_done $end
$var wire 1 ) div_by_zero $end
$var wire 1 C counter_en $end
$var wire 2 D alu_op [1:0] $end
$var wire 8 E addsub_result [7:0] $end
$var wire 1 F addsub_ovf $end
$var wire 1 G addsub_cout $end
$scope module ASU $end
$var wire 8 H A [7:0] $end
$var wire 8 I B [7:0] $end
$var wire 1 J c_in $end
$var wire 1 F overflow $end
$var wire 1 K sub $end
$var wire 8 L result [7:0] $end
$var wire 1 G cout $end
$var wire 8 M carry [7:0] $end
$var wire 8 N B_xor [7:0] $end
$scope module FA0 $end
$var wire 1 O a $end
$var wire 1 P b $end
$var wire 1 J cin $end
$var wire 1 Q cout $end
$var wire 1 R sum $end
$var wire 1 S w1 $end
$var wire 1 T w2 $end
$var wire 1 U w3 $end
$upscope $end
$scope module FA1 $end
$var wire 1 V a $end
$var wire 1 W b $end
$var wire 1 X cin $end
$var wire 1 Y cout $end
$var wire 1 Z sum $end
$var wire 1 [ w1 $end
$var wire 1 \ w2 $end
$var wire 1 ] w3 $end
$upscope $end
$scope module FA2 $end
$var wire 1 ^ a $end
$var wire 1 _ b $end
$var wire 1 ` cin $end
$var wire 1 a cout $end
$var wire 1 b sum $end
$var wire 1 c w1 $end
$var wire 1 d w2 $end
$var wire 1 e w3 $end
$upscope $end
$scope module FA3 $end
$var wire 1 f a $end
$var wire 1 g b $end
$var wire 1 h cin $end
$var wire 1 i cout $end
$var wire 1 j sum $end
$var wire 1 k w1 $end
$var wire 1 l w2 $end
$var wire 1 m w3 $end
$upscope $end
$scope module FA4 $end
$var wire 1 n a $end
$var wire 1 o b $end
$var wire 1 p cin $end
$var wire 1 q cout $end
$var wire 1 r sum $end
$var wire 1 s w1 $end
$var wire 1 t w2 $end
$var wire 1 u w3 $end
$upscope $end
$scope module FA5 $end
$var wire 1 v a $end
$var wire 1 w b $end
$var wire 1 x cin $end
$var wire 1 y cout $end
$var wire 1 z sum $end
$var wire 1 { w1 $end
$var wire 1 | w2 $end
$var wire 1 } w3 $end
$upscope $end
$scope module FA6 $end
$var wire 1 ~ a $end
$var wire 1 !" b $end
$var wire 1 "" cin $end
$var wire 1 #" cout $end
$var wire 1 $" sum $end
$var wire 1 %" w1 $end
$var wire 1 &" w2 $end
$var wire 1 '" w3 $end
$upscope $end
$scope module FA7 $end
$var wire 1 (" a $end
$var wire 1 )" b $end
$var wire 1 *" cin $end
$var wire 1 G cout $end
$var wire 1 +" sum $end
$var wire 1 ," w1 $end
$var wire 1 -" w2 $end
$var wire 1 ." w3 $end
$upscope $end
$upscope $end
$scope module CU $end
$var wire 1 * clk $end
$var wire 2 /" opcode [1:0] $end
$var wire 1 . reset $end
$var wire 1 / start $end
$var wire 1 ; mul_done $end
$var wire 1 B div_done $end
$var parameter 3 0" DONE $end
$var parameter 3 1" EXEC_AS $end
$var parameter 3 2" EXEC_DV $end
$var parameter 3 3" EXEC_MU $end
$var parameter 3 4" IDLE $end
$var parameter 3 5" LOAD $end
$var reg 2 6" alu_op [1:0] $end
$var reg 1 C counter_en $end
$var reg 1 ? load_A $end
$var reg 1 > load_B $end
$var reg 1 = load_M $end
$var reg 1 < load_Q $end
$var reg 1 9 mux_sel $end
$var reg 3 7" next_state [2:0] $end
$var reg 1 ! result_ready $end
$var reg 1 7 shift_en $end
$var reg 3 8" state [2:0] $end
$upscope $end
$scope module DIV $end
$var wire 1 * clk $end
$var wire 8 9" dividend [7:0] $end
$var wire 8 :" divisor [7:0] $end
$var wire 1 . reset $end
$var wire 1 ;" start $end
$var wire 1 ) div_by_zero $end
$var reg 8 <" A [7:0] $end
$var reg 8 =" M [7:0] $end
$var reg 8 >" Q [7:0] $end
$var reg 4 ?" count [3:0] $end
$var reg 1 B done $end
$var reg 8 @" quotient [7:0] $end
$var reg 8 A" remainder [7:0] $end
$var reg 1 B" running $end
$scope begin div_step $end
$var reg 8 C" A_next [7:0] $end
$var reg 8 D" A_shift [7:0] $end
$var reg 8 E" A_sub [7:0] $end
$var reg 1 F" q_bit $end
$upscope $end
$upscope $end
$scope module MULT $end
$var wire 1 * clk $end
$var wire 8 G" multiplicand [7:0] $end
$var wire 8 H" multiplier [7:0] $end
$var wire 1 . reset $end
$var wire 1 I" start $end
$var wire 9 J" M_ext [8:0] $end
$var reg 9 K" A [8:0] $end
$var reg 8 L" M [7:0] $end
$var reg 8 M" Q [7:0] $end
$var reg 1 N" Q1 $end
$var reg 4 O" count [3:0] $end
$var reg 1 ; done $end
$var reg 16 P" product [15:0] $end
$var reg 1 Q" running $end
$scope begin add_shift $end
$var reg 9 R" A_new [8:0] $end
$upscope $end
$scope begin sub_shift $end
$var reg 9 S" A_new [8:0] $end
$upscope $end
$upscope $end
$upscope $end
$scope task do_start $end
$upscope $end
$scope task wait_cycles $end
$var integer 32 T" i [31:0] $end
$var integer 32 U" n [31:0] $end
$upscope $end
$upscope $end
$enddefinitions $end
$comment Show the parameter values. $end
$dumpall
b1 5"
b0 4"
b11 3"
b100 2"
b10 1"
b101 0"
$end
#0
$dumpvars
b11 U"
b0 T"
bx S"
bx R"
xQ"
bx P"
bx O"
xN"
bx M"
bx L"
bx K"
b0 J"
0I"
b0 H"
b0 G"
xF"
bx E"
bx D"
bx C"
xB"
bx A"
bx @"
bx ?"
bx >"
bx ="
bx <"
0;"
b0 :"
b0 9"
bx 8"
b0 7"
b0 6"
b0 /"
0."
0-"
0,"
0+"
0*"
0)"
0("
0'"
0&"
0%"
0$"
0#"
0""
0!"
0~
0}
0|
0{
0z
0y
0x
0w
0v
0u
0t
0s
0r
0q
0p
0o
0n
0m
0l
0k
0j
0i
0h
0g
0f
0e
0d
0c
0b
0a
0`
0_
0^
0]
0\
0[
0Z
0Y
0X
0W
0V
0U
0T
0S
0R
0Q
0P
0O
b0 N
bz0000000 M
b0 L
0K
0J
b0 I
b0 H
0G
0F
b0 E
b0 D
0C
xB
bx A
bx @
0?
0>
0=
0<
x;
bx :
09
b0 8
07
bx 6
bx 5
b0 4
b0 3
b0 2
b0 1
b0 0
0/
1.
b0 -
b0 ,
b0 +
0*
1)
0(
0'
0&
1%
bx $
bx #
b0 "
0!
$end
#5000
b0 8"
b0 :
b0 P"
0;
0Q"
b0 O"
0N"
b0 L"
b0 M"
b0 K"
b0 #
b0 6
b0 @
b0 A"
b0 $
b0 5
b0 A
b0 @"
0B
0B"
b0 ?"
b0 ="
b0 >"
b0 <"
b1 T"
1*
#10000
0*
#15000
b10 T"
1*
#20000
0*
#25000
b11 T"
1*
#26000
b0 T"
b10 U"
0.
#30000
0*
#35000
b1 T"
1*
#40000
0*
#45000
b10 T"
1*
#46000
1z
1h
1x
1a
1q
1e
1u
1X
1`
1p
1Q
1Y
bz0011111 M
1i
0r
b101010 "
b101010 8
1T
1\
1l
1s
1P
1W
1g
1o
0R
1Z
0b
0%
b101010 E
b101010 L
1j
b11011 N
0S
0[
1c
0k
1O
1V
1^
1f
0)
b11011 ,
b11011 3
b11011 I
b11011 :"
b11011 H"
b1111 J"
b1111 +
b1111 2
b1111 H
b1111 9"
b1111 G"
#50000
0*
#55000
1*
#56000
b1 7"
1/
#60000
0*
#65000
1>
1?
b10 7"
b1 8"
1*
#66000
b10 7"
b0 T"
b11 U"
0/
#70000
0*
#75000
0>
0?
b101 7"
b10 8"
b1 T"
1*
#80000
0*
#85000
1!
b0 7"
b101 8"
b10 T"
1*
#90000
0*
#95000
0!
b0 8"
b11 T"
1*
#96000
1%
0z
0x
0r
0q
0h
b0 "
b0 8
0u
0s
0X
0`
0a
0p
0P
0W
0g
0o
0R
0Q
0Z
0]
0Y
0b
0e
b0 E
b0 L
0j
0m
bz0000000 M
0i
b0 N
0S
0T
0[
0\
0c
0k
0l
0O
0V
0^
0f
1)
b0 ,
b0 3
b0 I
b0 :"
b0 H"
b0 J"
b0 +
b0 2
b0 H
b0 9"
b0 G"
b1 1
#100000
0*
#105000
1*
#106000
b1 7"
1/
#110000
0*
#115000
1>
1?
b10 7"
b1 8"
1*
#116000
b10 7"
b0 T"
0/
#120000
0*
#125000
0>
0?
b101 7"
b10 8"
b1 T"
1*
#130000
0*
#135000
1!
b0 7"
b101 8"
b10 T"
1*
#140000
0*
#145000
0!
b0 8"
b11 T"
1*
#146000
1(
1G
0&
0F
1."
1*"
1b
1z
bz1000000 M
1#"
b101100 "
b101100 8
1c
1{
1&"
0'
1_
1w
1!"
1j
0$"
0%
b101100 E
b101100 L
0+"
b1100100 N
1k
0%"
1,"
1f
1~
1("
0)
b1100100 ,
b1100100 3
b1100100 I
b1100100 :"
b1100100 H"
b111001000 J"
b11001000 +
b11001000 2
b11001000 H
b11001000 9"
b11001000 G"
b10 1
#150000
0*
#155000
1*
#156000
b1 7"
1/
#160000
0*
#165000
1>
1?
b10 7"
b1 8"
1*
#166000
b10 7"
b0 T"
0/
#170000
0*
#175000
0>
0?
b101 7"
b10 8"
b1 T"
1*
#180000
0*
#185000
1!
b0 7"
b101 8"
b10 T"
1*
#190000
0*
#195000
0!
b0 8"
b11 T"
1*
#196000
0&
0F
1X
1Q
1`
1U
1Y
1b
1'"
b11110 "
b11110 8
1S
1\
0c
1""
1*"
0'
1(
1G
1P
1W
0_
1g
1)"
1Z
1j
1r
0z
1y
0$"
bz1100011 M
1#"
0+"
1."
b11110 E
b11110 L
0R
b11101011 N
0[
1k
1s
0{
1|
1%"
0&"
1,"
1J
1K
b1 D
b1 6"
1V
0f
1n
1v
0~
0("
b1 -
b1 4
b1 /"
b10100 ,
b10100 3
b10100 I
b10100 :"
b10100 H"
b110010 J"
b110010 +
b110010 2
b110010 H
b110010 9"
b110010 G"
b11 1
#200000
0*
#205000
1*
#206000
b1 7"
1/
#210000
0*
#215000
1>
1?
b10 7"
b1 8"
1*
#216000
b10 7"
b0 T"
0/
